cbebirr/__init__.py
cbebirr/cbebirr.py
cbebirr-0.0.19.dist-info/METADATA
cbebirr-0.0.19.dist-info/WHEEL
cbebirr-0.0.19.dist-info/top_level.txt
cbebirr-0.0.19.dist-info/RECORD
