Metadata-Version: 2.1
Name: cbebirr
Version: 0.0.19
Summary: CBEBirr integration
Author: Eba Alemayehu
Author-email: <ebaalemayhu3@gmail.com>
Keywords: python,cbebirr,payment,ethiopia,CBE,Commercial bank of Ethiopia
Classifier: Development Status :: 1 - Planning
Classifier: Intended Audience :: Developers
Classifier: Programming Language :: Python :: 3
Classifier: Operating System :: Unix
Classifier: Operating System :: MacOS :: MacOS X
Classifier: Operating System :: Microsoft :: Windows
Requires-Dist: xmltodict
Requires-Dist: requests
